odoo8_addon_social_media_dribbble-8.0.1.0.0.99.dev11-py3.8-nspkg.pth
odoo_addons/social_media_dribbble/README.rst
odoo_addons/social_media_dribbble/__init__.py
odoo_addons/social_media_dribbble/__openerp__.py
odoo_addons/social_media_dribbble/i18n/ar.po
odoo_addons/social_media_dribbble/i18n/bg.po
odoo_addons/social_media_dribbble/i18n/bs.po
odoo_addons/social_media_dribbble/i18n/ca.po
odoo_addons/social_media_dribbble/i18n/cs.po
odoo_addons/social_media_dribbble/i18n/da.po
odoo_addons/social_media_dribbble/i18n/de.po
odoo_addons/social_media_dribbble/i18n/el_GR.po
odoo_addons/social_media_dribbble/i18n/en_GB.po
odoo_addons/social_media_dribbble/i18n/es.po
odoo_addons/social_media_dribbble/i18n/es_AR.po
odoo_addons/social_media_dribbble/i18n/es_CL.po
odoo_addons/social_media_dribbble/i18n/es_CO.po
odoo_addons/social_media_dribbble/i18n/es_CR.po
odoo_addons/social_media_dribbble/i18n/es_DO.po
odoo_addons/social_media_dribbble/i18n/es_EC.po
odoo_addons/social_media_dribbble/i18n/es_MX.po
odoo_addons/social_media_dribbble/i18n/es_PE.po
odoo_addons/social_media_dribbble/i18n/et.po
odoo_addons/social_media_dribbble/i18n/fa.po
odoo_addons/social_media_dribbble/i18n/fi.po
odoo_addons/social_media_dribbble/i18n/fr.po
odoo_addons/social_media_dribbble/i18n/he.po
odoo_addons/social_media_dribbble/i18n/hr.po
odoo_addons/social_media_dribbble/i18n/hr_HR.po
odoo_addons/social_media_dribbble/i18n/hu.po
odoo_addons/social_media_dribbble/i18n/id.po
odoo_addons/social_media_dribbble/i18n/it.po
odoo_addons/social_media_dribbble/i18n/ja.po
odoo_addons/social_media_dribbble/i18n/ko.po
odoo_addons/social_media_dribbble/i18n/lt.po
odoo_addons/social_media_dribbble/i18n/lv.po
odoo_addons/social_media_dribbble/i18n/mk.po
odoo_addons/social_media_dribbble/i18n/mn.po
odoo_addons/social_media_dribbble/i18n/nb.po
odoo_addons/social_media_dribbble/i18n/pl.po
odoo_addons/social_media_dribbble/i18n/pt_BR.po
odoo_addons/social_media_dribbble/i18n/ru.po
odoo_addons/social_media_dribbble/i18n/sk.po
odoo8_addon_social_media_dribbble-8.0.1.0.0.99.dev11.dist-info/METADATA
odoo8_addon_social_media_dribbble-8.0.1.0.0.99.dev11.dist-info/WHEEL
odoo8_addon_social_media_dribbble-8.0.1.0.0.99.dev11.dist-info/namespace_packages.txt
odoo8_addon_social_media_dribbble-8.0.1.0.0.99.dev11.dist-info/top_level.txt
odoo8_addon_social_media_dribbble-8.0.1.0.0.99.dev11.dist-info/RECORD
